pyllmut/__init__.py
pyllmut/generator.py
pyllmut/mutation_report.py
pyllmut/model_lib/__init__.py
pyllmut/model_lib/gpt_4o.py
pyllmut/model_lib/gpt_4o_mini.py
pyllmut/model_lib/model_base.py
pyllmut/model_lib/model_manager.py
pyllmut/model_lib/model_response.py
pyllmut/model_lib/model_type.py
pyllmut/mutant_lib/__init__.py
pyllmut/mutant_lib/mutant_builder.py
pyllmut/mutant_lib/mutant_classifier.py
pyllmut/mutant_lib/mutant_info.py
pyllmut/mutant_lib/mutant_manager.py
pyllmut/mutant_lib/mutant_type.py
pyllmut/mutant_lib/prompt_info.py
pyllmut/mutant_lib/response_info.py
pyllmut/prompt_lib/__init__.py
pyllmut/prompt_lib/prompt_manager.py
pyllmut/prompt_lib/templates/prompt.template
pyllmut/response_lib/__init__.py
pyllmut/response_lib/model_response_parser.py
pyllmut/response_lib/response_manager.py
pyllmut/source_lib/__init__.py
pyllmut/source_lib/code_line_checker.py
pyllmut/source_lib/comment_remover.py
pyllmut/source_lib/line_context_finder.py
pyllmut/source_lib/source_manager.py
pyllmut-0.6.0.dist-info/LICENSE.txt
pyllmut-0.6.0.dist-info/METADATA
pyllmut-0.6.0.dist-info/WHEEL
pyllmut-0.6.0.dist-info/top_level.txt
pyllmut-0.6.0.dist-info/RECORD
