Metadata-Version: 2.1
Name: PyLLMut
Version: 0.6.0
Summary: An LLM-driven mutant generator library for Python
Author-email: Mohammad Rezaalipour <rezaalipour.mohammad@gmail.com>
Maintainer-email: Mohammad Rezaalipour <rezaalipour.mohammad@gmail.com>
License: The MIT License (MIT)
Project-URL: Homepage, https://pyllmut.readthedocs.io
Project-URL: Bug Reports, https://github.com/mohrez86/pyllmut/issues
Project-URL: Source, https://github.com/mohrez86/pyllmut
Keywords: LLM,Mutation,Python
Classifier: Development Status :: 3 - Alpha
Classifier: Intended Audience :: Developers
Classifier: Topic :: Software Development :: Build Tools
Classifier: License :: OSI Approved :: MIT License
Classifier: Programming Language :: Python :: 3
Classifier: Programming Language :: Python :: 3.7
Classifier: Programming Language :: Python :: 3.8
Classifier: Programming Language :: Python :: 3.9
Classifier: Programming Language :: Python :: 3.10
Classifier: Programming Language :: Python :: 3.11
Classifier: Programming Language :: Python :: 3.12
Classifier: Programming Language :: Python :: 3.13
Classifier: Programming Language :: Python :: 3 :: Only
Requires-Python: >=3.7
License-File: LICENSE.txt
Requires-Dist: openai <2.0.0,>=1.0.0
